[{"Title":"Tata Teaveda Ayurvedic Goodness Brahmi, Tulsi Tea Box","Image":"https://rukminim1.flixcart.com/image/280/280/k1118cw0/tea/s/t/8/250-teaveda-ayurvedic-goodness-regular-tea-tata-powder-original-imafkzzhyzrhv2jt.jpeg?q=70","_30jeq3":"₹96","_1mbxne":"250 g Box"},{"Title":"Tata Gold Tea Pouch","Image":"https://rukminim1.flixcart.com/image/280/280/jzsqky80/tea/9/j/n/750-gold-regular-tea-tata-leaves-original-imafjqj7z4mqtgjs.jpeg?q=70","_30jeq3":"₹376","_1mbxne":"750 g Pouch"},{"Title":"Red Label Natural Care Cardamom, Ginger, Liquorice, Tulsi Tea Box","Image":"https://rukminim1.flixcart.com/image/280/280/j9n3ekw0/tea/f/z/k/500-natural-care-regular-tea-powder-red-label-original-imaeze8cxf9hy5eb.jpeg?q=70","_30jeq3":"₹160","_1mbxne":"250 g Box"},{"Title":"Red Label Tea Box","Image":"https://rukminim1.flixcart.com/image/280/280/jk76j680/tea/d/q/w/500-na-regular-tea-leaves-red-label-original-imaf7hk6773kxpuh.jpeg?q=70","_30jeq3":"₹235","_1mbxne":"500 g Box"},{"Title":"Tata Agni Tea Pouch","Image":"","_30jeq3":"₹150","_1mbxne":"500 g Pouch"},{"Title":"Tata Premium Anokha Swad Tea Pouch","Image":"","_30jeq3":"₹260","_1mbxne":"500 g Pouch"},{"Title":"Taj Mahal Tea Box","Image":"","_30jeq3":"₹150","_1mbxne":"250 g Box"},{"Title":"Tata Gemini Tea Pouch","Image":"","_30jeq3":"₹378","_1mbxne":"1 kg Pouch"},{"Title":"Tata Agni Tea Pouch","Image":"","_30jeq3":"₹430","_1mbxne":"1 kg Pouch"},{"Title":"Tata Kanan Devan Strong Tea Pouch","Image":"","_30jeq3":"₹80","_1mbxne":"250 g Pouch"},{"Title":"3 Roses Natural Care Tulsi, Ginger, Cardamom Tea Box","Image":"","_30jeq3":"₹200","_1mbxne":"250 g Box"},{"Title":"Flipkart Supermart Food Essentials Premium Tea Pouch","Image":"","_30jeq3":"₹299","_1mbxne":"1 kg Pouch"},{"Title":"Society Jar Tea Plastic Bottle","Image":"","_30jeq3":"₹145","_1mbxne":"250 g Plastic Bottle"},{"Title":"Tata Chakra Gold Premium Tea Box","Image":"","_30jeq3":"₹309","_1mbxne":"500 g Box"},{"Title":"Flipkart Supermart Food Essentials Premium Tea Pouch","Image":"","_30jeq3":"₹149","_1mbxne":"500 g Pouch"},{"Title":"Dabur Honitus Hot Sip Herbal Infusion Box","Image":"","_30jeq3":"₹150","_1mbxne":"120 g Box"},{"Title":"3 Roses Tea Box","Image":"","_30jeq3":"₹180","_1mbxne":"250 g Box"},{"Title":"Tata Premium Tea Pouch","Image":"","_30jeq3":"₹705","_1mbxne":"1.5 kg Pouch"},{"Title":"Society Tea Pouch","Image":"","_30jeq3":"₹520","_1mbxne":"1 kg Pouch"},{"Title":"Society Masala Tea Plastic Bottle","Image":"","_30jeq3":"₹160","_1mbxne":"250 g Plastic Bottle"},{"Title":"Waghbakri Premium Leaf Tea Box","Image":"","_30jeq3":"₹275","_1mbxne":"500 g Box"},{"Title":"Tata Gold Care Tea Box","Image":"","_30jeq3":"₹140","_1mbxne":"250 g Box"},{"Title":"Society Tea Pouch","Image":"","_30jeq3":"₹119","_1mbxne":"250 g Pouch"},{"Title":"3 Roses Topstar Tea Box","Image":"","_30jeq3":"₹185","_1mbxne":"250 g Box"},{"Title":"tetley Lemon, Ginger, Mint Green Tea Bags Box","Image":"","_30jeq3":"₹132","_1mbxne":"25 Bags Box"},{"Title":"Waghbakri Spices Masala Tea Box","Image":"","_30jeq3":"₹150","_1mbxne":"250 g Box"},{"Title":"Nestea Peach Iced Tea Pouch","Image":"","_30jeq3":"₹169","_1mbxne":"400 g Pouch"},{"Title":"Lipton Honey, Lemon Green Tea Bags Box","Image":"","_30jeq3":"₹156","_1mbxne":"25 Bags Box"},{"Title":"Tata Tulsi Green Tea Bags Box","Image":"","_30jeq3":"₹116","_1mbxne":"25 Bags Box"},{"Title":"Society Lemon Iced Green Tea Pouch","Image":"","_30jeq3":"₹30","_1mbxne":"100 g Pouch"},{"Title":"tetley Lemon and Honey Green Tea Bags Box","Image":"","_30jeq3":"₹412","_1mbxne":"100 Bags Box"},{"Title":"tetley Ginger, Mint and Lemon Green Tea Bags Box","Image":"","_30jeq3":"₹412","_1mbxne":"100 Bags Box"},{"Title":"Lipton Loose Green Tea Box","Image":"","_30jeq3":"₹128","_1mbxne":"100 g Box"},{"Title":"tetley Refreshing Pure Original Green Tea Box","Image":"","_30jeq3":"₹280","_1mbxne":"250 g Box"},{"Title":"Society Leaf Tea Tea Pouch","Image":"","_30jeq3":"₹270","_1mbxne":"500 g Pouch"},{"Title":"Society Lemon Iced Black Tea Pouch","Image":"","_30jeq3":"₹30","_1mbxne":"100 g Pouch"},{"Title":"Society Premium Tea Pouch","Image":"","_30jeq3":"₹540","_1mbxne":"1 kg Pouch"},{"Title":"24 Mantra Green Tea Bags Box","Image":"","_30jeq3":"₹85","_1mbxne":"25 Bags Box"},{"Title":"Tata Chakra Gold Elaichi Tea Box","Image":"","_30jeq3":"₹75","_1mbxne":"100 g Box"},{"Title":"Tata Chakra Gold Activ Plus Lemon Grass, Garcinia, Amla Herbal Tea Box","Image":"","_30jeq3":"₹60","_1mbxne":"100 g Box"},{"Title":"Tata Premium Leaf Tea Box","Image":"","_30jeq3":"₹252","_1mbxne":"500 g Box"},{"Title":"Tata Tulsi Green Tea Pouch","Image":"","_30jeq3":"₹109","_1mbxne":"100 g Pouch"},{"Title":"Taj Mahal Tea Bags Box","Image":"","_30jeq3":"₹200","_1mbxne":"100 Bags Box"},{"Title":"Lipton Zest Lemon Green Tea Bags Box","Image":"","_30jeq3":"₹156","_1mbxne":"25 Bags Box"},{"Title":"Tata Kanan Devan Classic Tea Pouch","Image":"https://static-assets-web.flixcart.com/www/linchpin/fk-cp-zion/img/placeholder_fcebae.svg","_30jeq3":"₹142","_1mbxne":"500 g Pouch"},{"Title":"Lipton Tulsi Natura Tulsi Green Tea Bags Box","Image":"https://static-assets-web.flixcart.com/www/linchpin/fk-cp-zion/img/placeholder_fcebae.svg","_30jeq3":"₹156","_1mbxne":"25 Bags Box"},{"Title":"Eco Valley Assorted Green Tea Bags Box","Image":"https://static-assets-web.flixcart.com/www/linchpin/fk-cp-zion/img/placeholder_fcebae.svg","_30jeq3":"₹148","_1mbxne":"30 Bags Box"},{"Title":"tetley Original Real Taste Tea Bags Box","Image":"https://static-assets-web.flixcart.com/www/linchpin/fk-cp-zion/img/placeholder_fcebae.svg","_30jeq3":"₹258","_1mbxne":"250 Bags Box"},{"Title":"Lipton Darjeeling Tea Box","Image":"https://static-assets-web.flixcart.com/www/linchpin/fk-cp-zion/img/placeholder_fcebae.svg","_30jeq3":"₹427","_1mbxne":"250 g Box"},{"Title":"Lipton Green Tea Box","Image":"https://static-assets-web.flixcart.com/www/linchpin/fk-cp-zion/img/placeholder_fcebae.svg","_30jeq3":"₹330","_1mbxne":"250 g Box"},{"Title":"ORGANIC INDIA Tulsi Green Tea Bags Box","Image":"https://static-assets-web.flixcart.com/www/linchpin/fk-cp-zion/img/placeholder_fcebae.svg","_30jeq3":"₹174","_1mbxne":"25 Bags Box"},{"Title":"Tata Gold Mixture Tea Pouch","Image":"https://static-assets-web.flixcart.com/www/linchpin/fk-cp-zion/img/placeholder_fcebae.svg","_30jeq3":"₹98","_1mbxne":"250 g Pouch"},{"Title":"Everest Masala Tea Box","Image":"https://static-assets-web.flixcart.com/www/linchpin/fk-cp-zion/img/placeholder_fcebae.svg","_30jeq3":"₹55","_1mbxne":"50 g Box"},{"Title":"Tata Tea Gold Mixture Tea Pouch","Image":"https://static-assets-web.flixcart.com/www/linchpin/fk-cp-zion/img/placeholder_fcebae.svg","_30jeq3":"₹400","_1mbxne":"1 kg Pouch"},{"Title":"ORGANIC INDIA Tulsi Green Tea Tin","Image":"https://static-assets-web.flixcart.com/www/linchpin/fk-cp-zion/img/placeholder_fcebae.svg","_30jeq3":"₹230","_1mbxne":"100 g Tin"},{"Title":"Lipton Mint Burst Green Tea Bags Box","Image":"https://static-assets-web.flixcart.com/www/linchpin/fk-cp-zion/img/placeholder_fcebae.svg","_30jeq3":"₹126","_1mbxne":"25 Bags Box"},{"Title":"Taj Mahal Rich and Flavourful Tea Bags Box","Image":"https://static-assets-web.flixcart.com/www/linchpin/fk-cp-zion/img/placeholder_fcebae.svg","_30jeq3":"₹65","_1mbxne":"25 Bags Box"},{"Title":"Tata Chakra Gold Activ Plus Lemon Grass, Amla Tea Box","Image":"https://static-assets-web.flixcart.com/www/linchpin/fk-cp-zion/img/placeholder_fcebae.svg","_30jeq3":"₹145","_1mbxne":"250 g Box"},{"Title":"24 Mantra Green Tea Box","Image":"https://static-assets-web.flixcart.com/www/linchpin/fk-cp-zion/img/placeholder_fcebae.svg","_30jeq3":"₹102","_1mbxne":"100 g Box"},{"Title":"Waghbakri Mili Strong Tea Box","Image":"https://static-assets-web.flixcart.com/www/linchpin/fk-cp-zion/img/placeholder_fcebae.svg","_30jeq3":"₹113","_1mbxne":"250 g Box"},{"Title":"Tata Teaveda Ginger, Cardamom, Tulsi, Brahmi Masala Tea Pouch","Image":"https://static-assets-web.flixcart.com/www/linchpin/fk-cp-zion/img/placeholder_fcebae.svg","_30jeq3":"₹126","_1mbxne":"250 g Pouch"},{"Title":"Eco Valley Organic Sunny Lemon Green Tea Bags Box","Image":"https://static-assets-web.flixcart.com/www/linchpin/fk-cp-zion/img/placeholder_fcebae.svg","_30jeq3":"₹148","_1mbxne":"30 Bags Box"},{"Title":"tetley Immune with Added Vitamin C Green Tea Bags Box","Image":"https://static-assets-web.flixcart.com/www/linchpin/fk-cp-zion/img/placeholder_fcebae.svg","_30jeq3":"₹165","_1mbxne":"25 Bags Box"},{"Title":"Lipton Pure & Light Green Tea Bags Box","Image":"https://static-assets-web.flixcart.com/www/linchpin/fk-cp-zion/img/placeholder_fcebae.svg","_30jeq3":"₹517","_1mbxne":"100 Bags Box"},{"Title":"Nestea Peach Iced Tea Tetrapack","Image":"https://static-assets-web.flixcart.com/www/linchpin/fk-cp-zion/img/placeholder_fcebae.svg","_30jeq3":"₹20","_1mbxne":"200 ml Tetrapack"},{"Title":"Society Masala Tea Pouch","Image":"https://static-assets-web.flixcart.com/www/linchpin/fk-cp-zion/img/placeholder_fcebae.svg","_30jeq3":"₹63","_1mbxne":"100 g Pouch"},{"Title":"Eco Valley Divine Tulsi Green Tea Bags Box","Image":"https://static-assets-web.flixcart.com/www/linchpin/fk-cp-zion/img/placeholder_fcebae.svg","_30jeq3":"₹148","_1mbxne":"30 Bags Box"},{"Title":"tetley Green Tea Box","Image":"https://static-assets-web.flixcart.com/www/linchpin/fk-cp-zion/img/placeholder_fcebae.svg","_30jeq3":"₹400","_1mbxne":"500 g Box"},{"Title":"Waghbakri Ginger Premix Instant Tea Box","Image":"https://static-assets-web.flixcart.com/www/linchpin/fk-cp-zion/img/placeholder_fcebae.svg","_30jeq3":"₹140","_1mbxne":"10 Bags Box"},{"Title":"Dabur Vedic Suraksha Green Tea Bags Box","Image":"https://static-assets-web.flixcart.com/www/linchpin/fk-cp-zion/img/placeholder_fcebae.svg","_30jeq3":"₹150","_1mbxne":"25 Bags Box"},{"Title":"Tata Quick Chai Masala Tea Box","Image":"https://static-assets-web.flixcart.com/www/linchpin/fk-cp-zion/img/placeholder_fcebae.svg","_30jeq3":"₹99","_1mbxne":"10 Bags Box"},{"Title":"Vahdam Organic Turmeric Spiced 100% Natural Detox and Immunity Support Blend of Turmeric Powder & Fresh Spices Turmeric Herbal Tea Bags Box","Image":"https://static-assets-web.flixcart.com/www/linchpin/fk-cp-zion/img/placeholder_fcebae.svg","_30jeq3":"₹99","_1mbxne":"15 Bags Box"},{"Title":"Tata Tea Gold Tea Box","Image":"https://static-assets-web.flixcart.com/www/linchpin/fk-cp-zion/img/placeholder_fcebae.svg","_30jeq3":"₹283","_1mbxne":"500 g Box"},{"Title":"tetley Original Green Tea Box","Image":"https://static-assets-web.flixcart.com/www/linchpin/fk-cp-zion/img/placeholder_fcebae.svg","_30jeq3":"₹145","_1mbxne":"100 g Box"},{"Title":"tetley Uplifting Lemon, Honey Green Tea Bags Box","Image":"https://static-assets-web.flixcart.com/www/linchpin/fk-cp-zion/img/placeholder_fcebae.svg","_30jeq3":"₹165","_1mbxne":"25 Bags Box"},{"Title":"ORGANIC INDIA Original Tulsi Tea Bags Box","Image":"https://static-assets-web.flixcart.com/www/linchpin/fk-cp-zion/img/placeholder_fcebae.svg","_30jeq3":"₹148","_1mbxne":"25 Bags Box"},{"Title":"typhoo Luxurious Fruit Bracer Blackcurrant Infusion Tea Bags Box","Image":"https://static-assets-web.flixcart.com/www/linchpin/fk-cp-zion/img/placeholder_fcebae.svg","_30jeq3":"₹280","_1mbxne":"25 Bags Box"},{"Title":"Eco Valley Classic Green Tea Bags Box","Image":"https://static-assets-web.flixcart.com/www/linchpin/fk-cp-zion/img/placeholder_fcebae.svg","_30jeq3":"₹148","_1mbxne":"30 Bags Box"},{"Title":"Society One Minute Lemon Grass, Ginger Instant Tea Plastic Bottle","Image":"https://static-assets-web.flixcart.com/www/linchpin/fk-cp-zion/img/placeholder_fcebae.svg","_30jeq3":"₹198","_1mbxne":"500 g Plastic Bottle"},{"Title":"Vahdam Organic Detox Ayurvedic Kahwa Ginger, Tulsi Green Tea Bags Box","Image":"https://static-assets-web.flixcart.com/www/linchpin/fk-cp-zion/img/placeholder_fcebae.svg","_30jeq3":"₹191","_1mbxne":"15 Bags Box"},{"Title":"Tata Teaveda Ayurvedic Goodness Brahmi, Tulsi Tea Box","Image":"","_30jeq3":"₹96","_1mbxne":"250 g Box"},{"Title":"Tata Gold Tea Pouch","Image":"","_30jeq3":"₹376","_1mbxne":"750 g Pouch"},{"Title":"Red Label Natural Care Cardamom, Ginger, Liquorice, Tulsi Tea Box","Image":"","_30jeq3":"₹160","_1mbxne":"250 g Box"},{"Title":"Red Label Tea Box","Image":"","_30jeq3":"₹235","_1mbxne":"500 g Box"},{"Title":"Tata Agni Tea Pouch","Image":"https://static-assets-web.flixcart.com/www/linchpin/fk-cp-zion/img/placeholder_fcebae.svg","_30jeq3":"₹150","_1mbxne":"500 g Pouch"},{"Title":"Tata Premium Anokha Swad Tea Pouch","Image":"https://static-assets-web.flixcart.com/www/linchpin/fk-cp-zion/img/placeholder_fcebae.svg","_30jeq3":"₹260","_1mbxne":"500 g Pouch"},{"Title":"Taj Mahal Tea Box","Image":"https://static-assets-web.flixcart.com/www/linchpin/fk-cp-zion/img/placeholder_fcebae.svg","_30jeq3":"₹150","_1mbxne":"250 g Box"},{"Title":"Tata Gemini Tea Pouch","Image":"https://static-assets-web.flixcart.com/www/linchpin/fk-cp-zion/img/placeholder_fcebae.svg","_30jeq3":"₹378","_1mbxne":"1 kg Pouch"},{"Title":"Tata Agni Tea Pouch","Image":"https://static-assets-web.flixcart.com/www/linchpin/fk-cp-zion/img/placeholder_fcebae.svg","_30jeq3":"₹430","_1mbxne":"1 kg Pouch"},{"Title":"Tata Kanan Devan Strong Tea Pouch","Image":"https://static-assets-web.flixcart.com/www/linchpin/fk-cp-zion/img/placeholder_fcebae.svg","_30jeq3":"₹80","_1mbxne":"250 g Pouch"},{"Title":"3 Roses Natural Care Tulsi, Ginger, Cardamom Tea Box","Image":"https://static-assets-web.flixcart.com/www/linchpin/fk-cp-zion/img/placeholder_fcebae.svg","_30jeq3":"₹200","_1mbxne":"250 g Box"},{"Title":"Flipkart Supermart Food Essentials Premium Tea Pouch","Image":"https://static-assets-web.flixcart.com/www/linchpin/fk-cp-zion/img/placeholder_fcebae.svg","_30jeq3":"₹299","_1mbxne":"1 kg Pouch"},{"Title":"Society Jar Tea Plastic Bottle","Image":"https://static-assets-web.flixcart.com/www/linchpin/fk-cp-zion/img/placeholder_fcebae.svg","_30jeq3":"₹145","_1mbxne":"250 g Plastic Bottle"},{"Title":"Tata Chakra Gold Premium Tea Box","Image":"https://static-assets-web.flixcart.com/www/linchpin/fk-cp-zion/img/placeholder_fcebae.svg","_30jeq3":"₹309","_1mbxne":"500 g Box"},{"Title":"Flipkart Supermart Food Essentials Premium Tea Pouch","Image":"https://static-assets-web.flixcart.com/www/linchpin/fk-cp-zion/img/placeholder_fcebae.svg","_30jeq3":"₹149","_1mbxne":"500 g Pouch"},{"Title":"Dabur Honitus Hot Sip Herbal Infusion Box","Image":"https://static-assets-web.flixcart.com/www/linchpin/fk-cp-zion/img/placeholder_fcebae.svg","_30jeq3":"₹150","_1mbxne":"120 g Box"},{"Title":"3 Roses Tea Box","Image":"https://static-assets-web.flixcart.com/www/linchpin/fk-cp-zion/img/placeholder_fcebae.svg","_30jeq3":"₹180","_1mbxne":"250 g Box"},{"Title":"Tata Premium Tea Pouch","Image":"https://static-assets-web.flixcart.com/www/linchpin/fk-cp-zion/img/placeholder_fcebae.svg","_30jeq3":"₹705","_1mbxne":"1.5 kg Pouch"},{"Title":"Society Tea Pouch","Image":"https://static-assets-web.flixcart.com/www/linchpin/fk-cp-zion/img/placeholder_fcebae.svg","_30jeq3":"₹520","_1mbxne":"1 kg Pouch"},{"Title":"Society Masala Tea Plastic Bottle","Image":"https://static-assets-web.flixcart.com/www/linchpin/fk-cp-zion/img/placeholder_fcebae.svg","_30jeq3":"₹160","_1mbxne":"250 g Plastic Bottle"},{"Title":"Waghbakri Premium Leaf Tea Box","Image":"https://static-assets-web.flixcart.com/www/linchpin/fk-cp-zion/img/placeholder_fcebae.svg","_30jeq3":"₹275","_1mbxne":"500 g Box"},{"Title":"Tata Gold Care Tea Box","Image":"https://static-assets-web.flixcart.com/www/linchpin/fk-cp-zion/img/placeholder_fcebae.svg","_30jeq3":"₹140","_1mbxne":"250 g Box"},{"Title":"Society Tea Pouch","Image":"https://static-assets-web.flixcart.com/www/linchpin/fk-cp-zion/img/placeholder_fcebae.svg","_30jeq3":"₹119","_1mbxne":"250 g Pouch"},{"Title":"3 Roses Topstar Tea Box","Image":"https://static-assets-web.flixcart.com/www/linchpin/fk-cp-zion/img/placeholder_fcebae.svg","_30jeq3":"₹185","_1mbxne":"250 g Box"},{"Title":"tetley Lemon, Ginger, Mint Green Tea Bags Box","Image":"https://static-assets-web.flixcart.com/www/linchpin/fk-cp-zion/img/placeholder_fcebae.svg","_30jeq3":"₹132","_1mbxne":"25 Bags Box"},{"Title":"Waghbakri Spices Masala Tea Box","Image":"https://static-assets-web.flixcart.com/www/linchpin/fk-cp-zion/img/placeholder_fcebae.svg","_30jeq3":"₹150","_1mbxne":"250 g Box"},{"Title":"Nestea Peach Iced Tea Pouch","Image":"https://static-assets-web.flixcart.com/www/linchpin/fk-cp-zion/img/placeholder_fcebae.svg","_30jeq3":"₹169","_1mbxne":"400 g Pouch"},{"Title":"Lipton Honey, Lemon Green Tea Bags Box","Image":"https://static-assets-web.flixcart.com/www/linchpin/fk-cp-zion/img/placeholder_fcebae.svg","_30jeq3":"₹156","_1mbxne":"25 Bags Box"},{"Title":"Tata Tulsi Green Tea Bags Box","Image":"https://static-assets-web.flixcart.com/www/linchpin/fk-cp-zion/img/placeholder_fcebae.svg","_30jeq3":"₹116","_1mbxne":"25 Bags Box"},{"Title":"Society Lemon Iced Green Tea Pouch","Image":"https://static-assets-web.flixcart.com/www/linchpin/fk-cp-zion/img/placeholder_fcebae.svg","_30jeq3":"₹30","_1mbxne":"100 g Pouch"},{"Title":"tetley Lemon and Honey Green Tea Bags Box","Image":"https://static-assets-web.flixcart.com/www/linchpin/fk-cp-zion/img/placeholder_fcebae.svg","_30jeq3":"₹412","_1mbxne":"100 Bags Box"},{"Title":"tetley Ginger, Mint and Lemon Green Tea Bags Box","Image":"https://static-assets-web.flixcart.com/www/linchpin/fk-cp-zion/img/placeholder_fcebae.svg","_30jeq3":"₹412","_1mbxne":"100 Bags Box"},{"Title":"Lipton Loose Green Tea Box","Image":"https://static-assets-web.flixcart.com/www/linchpin/fk-cp-zion/img/placeholder_fcebae.svg","_30jeq3":"₹128","_1mbxne":"100 g Box"},{"Title":"tetley Refreshing Pure Original Green Tea Box","Image":"https://static-assets-web.flixcart.com/www/linchpin/fk-cp-zion/img/placeholder_fcebae.svg","_30jeq3":"₹280","_1mbxne":"250 g Box"},{"Title":"Society Leaf Tea Tea Pouch","Image":"https://static-assets-web.flixcart.com/www/linchpin/fk-cp-zion/img/placeholder_fcebae.svg","_30jeq3":"₹270","_1mbxne":"500 g Pouch"},{"Title":"Society Lemon Iced Black Tea Pouch","Image":"https://static-assets-web.flixcart.com/www/linchpin/fk-cp-zion/img/placeholder_fcebae.svg","_30jeq3":"₹30","_1mbxne":"100 g Pouch"},{"Title":"Society Premium Tea Pouch","Image":"https://static-assets-web.flixcart.com/www/linchpin/fk-cp-zion/img/placeholder_fcebae.svg","_30jeq3":"₹540","_1mbxne":"1 kg Pouch"},{"Title":"24 Mantra Green Tea Bags Box","Image":"https://static-assets-web.flixcart.com/www/linchpin/fk-cp-zion/img/placeholder_fcebae.svg","_30jeq3":"₹85","_1mbxne":"25 Bags Box"},{"Title":"Tata Chakra Gold Elaichi Tea Box","Image":"https://static-assets-web.flixcart.com/www/linchpin/fk-cp-zion/img/placeholder_fcebae.svg","_30jeq3":"₹75","_1mbxne":"100 g Box"},{"Title":"Tata Chakra Gold Activ Plus Lemon Grass, Garcinia, Amla Herbal Tea Box","Image":"https://static-assets-web.flixcart.com/www/linchpin/fk-cp-zion/img/placeholder_fcebae.svg","_30jeq3":"₹60","_1mbxne":"100 g Box"}]